dbfn/ReactionBook.py
dbfn/__init__.py
dbfn-1.0.6.dist-info/LICENSE.md
dbfn-1.0.6.dist-info/METADATA
dbfn-1.0.6.dist-info/WHEEL
dbfn-1.0.6.dist-info/top_level.txt
dbfn-1.0.6.dist-info/RECORD
