Metadata-Version: 2.1
Name: dbfn
Version: 1.0.6
Summary: Discord Bot Functions. Includes reaction books with more feature to be added
Home-page: https://github.com/judev1/dbfn
Author: Jude BC
Author-email: jude.version1.0@gmail.com
License: BSD 2-clause
Platform: UNKNOWN
Classifier: Development Status :: 5 - Production/Stable
Classifier: Intended Audience :: Developers
Classifier: License :: OSI Approved :: GNU General Public License v3 (GPLv3)
Classifier: Operating System :: Microsoft
Classifier: Programming Language :: Python :: 2
Classifier: Programming Language :: Python :: 3
